{"year":2020,"area":"Västra Göteborg område 2","schools":[{"id":158,"name":"Allmänna Vägen 40 förskola","responseRate":73,"respondents":19,"areaMeans":[{"area":"Trygghet och trivsel","mean":4.6},{"area":"Utveckling och lärande","mean":4.15},{"area":"Inflytande","mean":4.39},{"area":"Relation och kommunikation","mean":4.32},{"area":"Helhetsomdöme","mean":4.37}]},{"id":161,"name":"Djurgårdsgatan 29 förskola","responseRate":78,"respondents":25,"areaMeans":[{"area":"Trygghet och trivsel","mean":4.34},{"area":"Utveckling och lärande","mean":3.9},{"area":"Inflytande","mean":4.21},{"area":"Relation och kommunikation","mean":4.11},{"area":"Helhetsomdöme","mean":4.2}]},{"id":175,"name":"Mariebergsgatan 7 förskola","responseRate":77,"respondents":56,"areaMeans":[{"area":"Trygghet och trivsel","mean":4.28},{"area":"Utveckling och lärande","mean":4.03},{"area":"Inflytande","mean":4.13},{"area":"Relation och kommunikation","mean":4.17},{"area":"Helhetsomdöme","mean":4.3}]},{"id":183,"name":"Seglaregatan 17 förskola","responseRate":68,"respondents":41,"areaMeans":[{"area":"Trygghet och trivsel","mean":4.3},{"area":"Utveckling och lärande","mean":4.12},{"area":"Inflytande","mean":4.26},{"area":"Relation och kommunikation","mean":3.91},{"area":"Helhetsomdöme","mean":4.28}]},{"id":184,"name":"Seglaregatan 5 förskola","responseRate":70,"respondents":26,"areaMeans":[{"area":"Trygghet och trivsel","mean":4.58},{"area":"Utveckling och lärande","mean":4.1},{"area":"Inflytande","mean":4.22},{"area":"Relation och kommunikation","mean":4.42},{"area":"Helhetsomdöme","mean":4.52}]},{"id":192,"name":"Styrmansgatan 13 förskola","responseRate":74,"respondents":23,"areaMeans":[{"area":"Trygghet och trivsel","mean":4.51},{"area":"Utveckling och lärande","mean":4},{"area":"Inflytande","mean":4.28},{"area":"Relation och kommunikation","mean":4.33},{"area":"Helhetsomdöme","mean":4.52}]},{"id":193,"name":"Styrmansgatan 21 A förskola","responseRate":66,"respondents":41,"areaMeans":[{"area":"Trygghet och trivsel","mean":4.24},{"area":"Utveckling och lärande","mean":3.99},{"area":"Inflytande","mean":4.18},{"area":"Relation och kommunikation","mean":4.15},{"area":"Helhetsomdöme","mean":3.95}]},{"id":200,"name":"Tellgrensgatan 7 förskola","responseRate":83,"respondents":53,"areaMeans":[{"area":"Trygghet och trivsel","mean":4.28},{"area":"Utveckling och lärande","mean":3.82},{"area":"Inflytande","mean":4.03},{"area":"Relation och kommunikation","mean":4.19},{"area":"Helhetsomdöme","mean":4.15}]},{"id":433,"name":"Lindebovägen 1 förskola","responseRate":82,"respondents":59,"areaMeans":[{"area":"Trygghet och trivsel","mean":4.28},{"area":"Utveckling och lärande","mean":3.94},{"area":"Inflytande","mean":4.13},{"area":"Relation och kommunikation","mean":4.04},{"area":"Helhetsomdöme","mean":3.94}]},{"id":444,"name":"Tunnlandsgatan 3 förskola","responseRate":69,"respondents":33,"areaMeans":[{"area":"Trygghet och trivsel","mean":4.55},{"area":"Utveckling och lärande","mean":4.44},{"area":"Inflytande","mean":4.35},{"area":"Relation och kommunikation","mean":4.44},{"area":"Helhetsomdöme","mean":4.65}]},{"id":451,"name":"Barytongatan 2 förskola","responseRate":63,"respondents":83,"areaMeans":[{"area":"Trygghet och trivsel","mean":4.33},{"area":"Utveckling och lärande","mean":4.06},{"area":"Inflytande","mean":4.17},{"area":"Relation och kommunikation","mean":4.05},{"area":"Helhetsomdöme","mean":4.31}]},{"id":452,"name":"Bildradiogatan 38 förskola","responseRate":56,"respondents":27,"areaMeans":[{"area":"Trygghet och trivsel","mean":4.17},{"area":"Utveckling och lärande","mean":4.11},{"area":"Inflytande","mean":4.03},{"area":"Relation och kommunikation","mean":3.94},{"area":"Helhetsomdöme","mean":4.26}]},{"id":453,"name":"Brattenskogen 6 förskola","responseRate":61,"respondents":14,"areaMeans":[{"area":"Trygghet och trivsel","mean":4.52},{"area":"Utveckling och lärande","mean":4.67},{"area":"Inflytande","mean":4.37},{"area":"Relation och kommunikation","mean":4.55},{"area":"Helhetsomdöme","mean":4.83}]},{"id":454,"name":"Bronsåldersgatan 27 förskola","responseRate":67,"respondents":18,"areaMeans":[{"area":"Trygghet och trivsel","mean":4.34},{"area":"Utveckling och lärande","mean":4.19},{"area":"Inflytande","mean":4.06},{"area":"Relation och kommunikation","mean":4.29},{"area":"Helhetsomdöme","mean":4.42}]},{"id":457,"name":"Fiolgatan 20 förskola","responseRate":71,"respondents":48,"areaMeans":[{"area":"Trygghet och trivsel","mean":4},{"area":"Utveckling och lärande","mean":3.82},{"area":"Inflytande","mean":4.03},{"area":"Relation och kommunikation","mean":3.92},{"area":"Helhetsomdöme","mean":3.72}]},{"id":458,"name":"Fredagstomten 23 förskola","responseRate":77,"respondents":43,"areaMeans":[{"area":"Trygghet och trivsel","mean":4.06},{"area":"Utveckling och lärande","mean":4.08},{"area":"Inflytande","mean":3.93},{"area":"Relation och kommunikation","mean":3.99},{"area":"Helhetsomdöme","mean":3.99}]},{"id":459,"name":"Gnistgatan 3 förskola","responseRate":60,"respondents":40,"areaMeans":[{"area":"Trygghet och trivsel","mean":4.15},{"area":"Utveckling och lärande","mean":4.14},{"area":"Inflytande","mean":4.05},{"area":"Relation och kommunikation","mean":4.01},{"area":"Helhetsomdöme","mean":4.12}]},{"id":460,"name":"Grållekroksvägen 4 förskola","responseRate":76,"respondents":13,"areaMeans":[{"area":"Trygghet och trivsel","mean":4.66},{"area":"Utveckling och lärande","mean":4.59},{"area":"Inflytande","mean":4.61},{"area":"Relation och kommunikation","mean":4.72},{"area":"Helhetsomdöme","mean":4.85}]},{"id":463,"name":"Körevägen 15 förskola","responseRate":73,"respondents":16,"areaMeans":[{"area":"Trygghet och trivsel","mean":4},{"area":"Utveckling och lärande","mean":3.67},{"area":"Inflytande","mean":3.58},{"area":"Relation och kommunikation","mean":3.41},{"area":"Helhetsomdöme","mean":3.75}]},{"id":464,"name":"Marklandsgatan 41 förskola","responseRate":69,"respondents":27,"areaMeans":[{"area":"Trygghet och trivsel","mean":4.52},{"area":"Utveckling och lärande","mean":4.2},{"area":"Inflytande","mean":4.32},{"area":"Relation och kommunikation","mean":4.27},{"area":"Helhetsomdöme","mean":4.55}]},{"id":466,"name":"Munspelsgatan 6 förskola","responseRate":35,"respondents":43,"areaMeans":[{"area":"Trygghet och trivsel","mean":4.18},{"area":"Utveckling och lärande","mean":3.83},{"area":"Inflytande","mean":3.99},{"area":"Relation och kommunikation","mean":3.99},{"area":"Helhetsomdöme","mean":3.93}]},{"id":468,"name":"Opalgatan 100 förskola","responseRate":35,"respondents":15,"areaMeans":[{"area":"Trygghet och trivsel","mean":4.29},{"area":"Utveckling och lärande","mean":4.02},{"area":"Inflytande","mean":4.04},{"area":"Relation och kommunikation","mean":4.1},{"area":"Helhetsomdöme","mean":4.24}]},{"id":469,"name":"Orkestergatan 35 förskola","responseRate":67,"respondents":40,"areaMeans":[{"area":"Trygghet och trivsel","mean":4.02},{"area":"Utveckling och lärande","mean":3.71},{"area":"Inflytande","mean":3.63},{"area":"Relation och kommunikation","mean":3.55},{"area":"Helhetsomdöme","mean":3.57}]},{"id":472,"name":"Sjupundsgatan 28 förskola","responseRate":63,"respondents":83,"areaMeans":[{"area":"Trygghet och trivsel","mean":4.15},{"area":"Utveckling och lärande","mean":4.08},{"area":"Inflytande","mean":4},{"area":"Relation och kommunikation","mean":3.86},{"area":"Helhetsomdöme","mean":4.02}]},{"id":475,"name":"Smithska Vägen 14 B förskola","responseRate":60,"respondents":36,"areaMeans":[{"area":"Trygghet och trivsel","mean":4.12},{"area":"Utveckling och lärande","mean":3.73},{"area":"Inflytande","mean":3.84},{"area":"Relation och kommunikation","mean":3.91},{"area":"Helhetsomdöme","mean":3.76}]},{"id":476,"name":"Stenskärsgatan 2 förskola","responseRate":76,"respondents":39,"areaMeans":[{"area":"Trygghet och trivsel","mean":4.2},{"area":"Utveckling och lärande","mean":3.88},{"area":"Inflytande","mean":3.84},{"area":"Relation och kommunikation","mean":4},{"area":"Helhetsomdöme","mean":4.25}]},{"id":477,"name":"Stjärnbåtsgatan 7 förskola","responseRate":57,"respondents":38,"areaMeans":[{"area":"Trygghet och trivsel","mean":4.5},{"area":"Utveckling och lärande","mean":4.32},{"area":"Inflytande","mean":4.48},{"area":"Relation och kommunikation","mean":4.35},{"area":"Helhetsomdöme","mean":4.39}]},{"id":478,"name":"Topasgatan 1 förskola","responseRate":40,"respondents":29,"areaMeans":[{"area":"Trygghet och trivsel","mean":4.44},{"area":"Utveckling och lärande","mean":4.34},{"area":"Inflytande","mean":4.28},{"area":"Relation och kommunikation","mean":4.32},{"area":"Helhetsomdöme","mean":4.5}]},{"id":479,"name":"Transistorgatan 2 förskola","responseRate":72,"respondents":73,"areaMeans":[{"area":"Trygghet och trivsel","mean":4.3},{"area":"Utveckling och lärande","mean":4.24},{"area":"Inflytande","mean":4.13},{"area":"Relation och kommunikation","mean":4.21},{"area":"Helhetsomdöme","mean":4.3}]},{"id":480,"name":"Töttefällevägen 2 förskola","responseRate":56,"respondents":29,"areaMeans":[{"area":"Trygghet och trivsel","mean":4.56},{"area":"Utveckling och lärande","mean":4.46},{"area":"Inflytande","mean":4.56},{"area":"Relation och kommunikation","mean":4.51},{"area":"Helhetsomdöme","mean":4.63}]},{"id":481,"name":"Valthornsgatan 3 förskola","responseRate":39,"respondents":29,"areaMeans":[{"area":"Trygghet och trivsel","mean":4.24},{"area":"Utveckling och lärande","mean":4.07},{"area":"Inflytande","mean":4.06},{"area":"Relation och kommunikation","mean":3.96},{"area":"Helhetsomdöme","mean":4.07}]},{"id":482,"name":"Våglängdsgatan 7 förskola","responseRate":71,"respondents":25,"areaMeans":[{"area":"Trygghet och trivsel","mean":4.63},{"area":"Utveckling och lärande","mean":4.25},{"area":"Inflytande","mean":4.41},{"area":"Relation och kommunikation","mean":4.18},{"area":"Helhetsomdöme","mean":4.36}]},{"id":483,"name":"Åkereds Skolväg 20 förskola","responseRate":73,"respondents":47,"areaMeans":[{"area":"Trygghet och trivsel","mean":4.27},{"area":"Utveckling och lärande","mean":4.07},{"area":"Inflytande","mean":4.16},{"area":"Relation och kommunikation","mean":4.17},{"area":"Helhetsomdöme","mean":4.07}]},{"id":551,"name":"Koopmansgatan 22 förskola","responseRate":49,"respondents":21,"areaMeans":[{"area":"Trygghet och trivsel","mean":4.35},{"area":"Utveckling och lärande","mean":3.84},{"area":"Inflytande","mean":4.2},{"area":"Relation och kommunikation","mean":4.03},{"area":"Helhetsomdöme","mean":4.04}]},{"id":789,"name":"Jydeklovan 2 förskola","responseRate":50,"respondents":15,"areaMeans":[{"area":"Trygghet och trivsel","mean":4.6},{"area":"Utveckling och lärande","mean":4.29},{"area":"Inflytande","mean":4.33},{"area":"Relation och kommunikation","mean":4.15},{"area":"Helhetsomdöme","mean":4.5}]},{"id":791,"name":"Marklandsgatan 21 förskola","responseRate":63,"respondents":29,"areaMeans":[{"area":"Trygghet och trivsel","mean":4.04},{"area":"Utveckling och lärande","mean":3.5},{"area":"Inflytande","mean":3.73},{"area":"Relation och kommunikation","mean":3.74},{"area":"Helhetsomdöme","mean":3.79}]},{"id":792,"name":"Melongatan 3 förskola","responseRate":67,"respondents":61,"areaMeans":[{"area":"Trygghet och trivsel","mean":4.56},{"area":"Utveckling och lärande","mean":4.36},{"area":"Inflytande","mean":4.37},{"area":"Relation och kommunikation","mean":4.48},{"area":"Helhetsomdöme","mean":4.64}]},{"id":803,"name":"Spannlandsgatan 1 förskola","responseRate":57,"respondents":16,"areaMeans":[{"area":"Trygghet och trivsel","mean":4.21},{"area":"Utveckling och lärande","mean":3.71},{"area":"Inflytande","mean":3.86},{"area":"Relation och kommunikation","mean":3.85},{"area":"Helhetsomdöme","mean":4.06}]},{"id":808,"name":"Tärneskärsgatan 4 förskola","responseRate":76,"respondents":26,"areaMeans":[{"area":"Trygghet och trivsel","mean":4.48},{"area":"Utveckling och lärande","mean":4.24},{"area":"Inflytande","mean":4.14},{"area":"Relation och kommunikation","mean":4.23},{"area":"Helhetsomdöme","mean":4.44}]},{"id":1527,"name":"Gånglåten 31 Nattomsorg","responseRate":47,"respondents":7,"areaMeans":[{"area":"Trygghet och trivsel","mean":4.57},{"area":"Utveckling och lärande","mean":4.37},{"area":"Inflytande","mean":4.31},{"area":"Relation och kommunikation","mean":4.32},{"area":"Helhetsomdöme","mean":4.64}]},{"id":1603,"name":"Draken","responseRate":50,"respondents":11,"areaMeans":[{"area":"Trygghet och trivsel","mean":4.23},{"area":"Utveckling och lärande","mean":3.63},{"area":"Inflytande","mean":3.95},{"area":"Relation och kommunikation","mean":3.93},{"area":"Helhetsomdöme","mean":3.87}]},{"id":1842,"name":"Räven","responseRate":60,"respondents":9,"areaMeans":[{"area":"Trygghet och trivsel","mean":3.81},{"area":"Utveckling och lärande","mean":3.01},{"area":"Inflytande","mean":3.28},{"area":"Relation och kommunikation","mean":2.95},{"area":"Helhetsomdöme","mean":2.61}]},{"id":2450,"name":"Kommendörsgatan 9C","responseRate":85,"respondents":17,"areaMeans":[{"area":"Trygghet och trivsel","mean":4.55},{"area":"Utveckling och lärande","mean":3.97},{"area":"Inflytande","mean":4.34},{"area":"Relation och kommunikation","mean":4.33},{"area":"Helhetsomdöme","mean":3.96}]},{"id":2466,"name":"Melongatan 90","responseRate":69,"respondents":29,"areaMeans":[{"area":"Trygghet och trivsel","mean":4.42},{"area":"Utveckling och lärande","mean":4.48},{"area":"Inflytande","mean":4.32},{"area":"Relation och kommunikation","mean":4.24},{"area":"Helhetsomdöme","mean":4.48}]},{"id":2475,"name":"Nymilsgatan 6","responseRate":62,"respondents":13,"areaMeans":[{"area":"Trygghet och trivsel","mean":4.48},{"area":"Utveckling och lärande","mean":4.14},{"area":"Inflytande","mean":4.19},{"area":"Relation och kommunikation","mean":4.29},{"area":"Helhetsomdöme","mean":4.44}]},{"id":4427,"name":"Annas Gård 6","responseRate":60,"respondents":12,"areaMeans":[{"area":"Trygghet och trivsel","mean":4.5},{"area":"Utveckling och lärande","mean":4.24},{"area":"Inflytande","mean":4.21},{"area":"Relation och kommunikation","mean":4.25},{"area":"Helhetsomdöme","mean":4.36}]},{"id":4460,"name":"Standargatan 10","responseRate":71,"respondents":17,"areaMeans":[{"area":"Trygghet och trivsel","mean":4.22},{"area":"Utveckling och lärande","mean":3.49},{"area":"Inflytande","mean":3.95},{"area":"Relation och kommunikation","mean":4.11},{"area":"Helhetsomdöme","mean":4.22}]},{"id":4626,"name":"Gitarrgatan 5 förskola","responseRate":45,"respondents":19,"areaMeans":[{"area":"Trygghet och trivsel","mean":4.32},{"area":"Utveckling och lärande","mean":4},{"area":"Inflytande","mean":4.12},{"area":"Relation och kommunikation","mean":3.95},{"area":"Helhetsomdöme","mean":4.22}]},{"id":4839,"name":"Bronsåldersgatan 82 förskola","responseRate":50,"respondents":14,"areaMeans":[{"area":"Trygghet och trivsel","mean":4.31},{"area":"Utveckling och lärande","mean":4.04},{"area":"Inflytande","mean":4.26},{"area":"Relation och kommunikation","mean":4.23},{"area":"Helhetsomdöme","mean":4.33}]},{"id":4847,"name":"Karneolgatan 79 förskola","responseRate":40,"respondents":19,"areaMeans":[{"area":"Trygghet och trivsel","mean":4.37},{"area":"Utveckling och lärande","mean":4.29},{"area":"Inflytande","mean":4.26},{"area":"Relation och kommunikation","mean":4.27},{"area":"Helhetsomdöme","mean":4.14}]},{"id":4873,"name":"Åkereds Skolväg 16 förskola","responseRate":73,"respondents":16,"areaMeans":[{"area":"Trygghet och trivsel","mean":4.51},{"area":"Utveckling och lärande","mean":4.16},{"area":"Inflytande","mean":4.29},{"area":"Relation och kommunikation","mean":4.42},{"area":"Helhetsomdöme","mean":4.75}]}]}