{"id":11167,"schoolId":5028,"schoolName":"Salsavägen 47 förskola","areaName":"Angered","year":2017,"reportType":"unit","unitName":"Rapport_Pandan_empty","pdfUrl":"https://enkater.goteborg.se/2017/BARN__F%c3%96RSKOLA/Angered/Salsav%c3%a4gen%2047%20f%c3%b6rskola/Rapport_Pandan_empty.pdf","scale":"1-7","metadata":null,"means":[],"responses":[],"genderSplit":[],"importantQuestions":[],"unitMeans":[],"relatedReports":[{"reportId":11168,"reportType":"unit","unitName":"Rapport_Salsavägen 47 förskola","schoolName":"Salsavägen 47 förskola"},{"reportId":11169,"reportType":"unit","unitName":"Rapport_Ugglan_empty","schoolName":"Salsavägen 47 förskola"},{"reportId":11170,"reportType":"unit","unitName":"Rapport_Zebran_empty","schoolName":"Salsavägen 47 förskola"}]}