{"id":13999,"schoolId":5654,"schoolName":"18_Lundby","areaName":"99_ANNAN_REGI","year":2007,"reportType":"unit","unitName":"Lundby Barn_tabell1_priv_2007","pdfUrl":"https://enkater.goteborg.se/2007/BARN__F%c3%96RSKOLA/99_ANNAN_REGI/18_Lundby/Lundby%20Barn_tabell1_priv_2007.xls","scale":"1-3","metadata":null,"means":[],"responses":[],"genderSplit":[],"importantQuestions":[],"unitMeans":[],"relatedReports":[{"reportId":20372,"reportType":"unit","unitName":"Lundby Förskola_tabell1_priv_2007","schoolName":"18_Lundby"},{"reportId":16932,"reportType":"unit","unitName":"Djungeln","schoolName":"Djungeln"},{"reportId":16933,"reportType":"unit","unitName":"Helge","schoolName":"Helge"},{"reportId":16934,"reportType":"unit","unitName":"Junibacken","schoolName":"Junibacken"},{"reportId":16935,"reportType":"unit","unitName":"Gryningen","schoolName":"Gryningen"},{"reportId":16936,"reportType":"unit","unitName":"Lokomotivet","schoolName":"Lokomotivet"},{"reportId":16937,"reportType":"unit","unitName":"Sverigefinska förskolan","schoolName":"Sverigefinska förskolan"},{"reportId":17050,"reportType":"unit","unitName":"Djungeln","schoolName":"Djungeln"},{"reportId":17051,"reportType":"unit","unitName":"Helge","schoolName":"Helge"},{"reportId":17052,"reportType":"unit","unitName":"Junibacken","schoolName":"Junibacken"},{"reportId":17053,"reportType":"unit","unitName":"Gryningen","schoolName":"Gryningen"},{"reportId":17054,"reportType":"unit","unitName":"Lokomotivet","schoolName":"Lokomotivet"},{"reportId":17055,"reportType":"unit","unitName":"Sverigefinska förskolan","schoolName":"Sverigefinska förskolan"}]}