{"id":15189,"schoolId":6618,"schoolName":"Hästevik (s)","areaName":"16_Torslanda","year":2008,"reportType":"unit","unitName":"HÄSTEVIK (S)","pdfUrl":"https://enkater.goteborg.se/2008/BARN__F%c3%96RSKOLA/16_Torslanda/Torslanda%20Barn_F%c3%b6rskola_TABELL_kom_2008.xls#T1016021100","scale":"1-3","metadata":{"responseRate":null,"respondents":38,"totalInvited":null,"birthYearDistribution":null,"childGenderDistribution":null,"parentGenderDistribution":null},"means":[{"question":"tycker du att det är roligt att vara på förskolan/ familjedaghemmet?","area":null,"gr":null,"goteborg":null,"district":2.77386,"school":2.65789,"normalized":82.89,"history":{}},{"question":"har du några bra kompisar på förskolan/ familjedaghemmet?","area":null,"gr":null,"goteborg":null,"district":2.88329,"school":2.94595,"normalized":97.3,"history":{}},{"question":"brukar ni göra roliga saker när ni är inne på förskolan/ familjedaghemmet?","area":null,"gr":null,"goteborg":null,"district":2.83004,"school":2.97297,"normalized":98.65,"history":{}},{"question":"får du själv bestämma vad du vill leka på förskolan/ familjedaghemmet?","area":null,"gr":null,"goteborg":null,"district":2.49911,"school":2.4,"normalized":70,"history":{}},{"question":"finns det roliga saker att leka med på förskolan/ familjedaghemmet?","area":null,"gr":null,"goteborg":null,"district":2.77988,"school":2.78378,"normalized":89.19,"history":{}},{"question":"vad tycker du om att vara ute och leka på förskolan/familjedaghemmet?","area":null,"gr":null,"goteborg":null,"district":2.62046,"school":2.67568,"normalized":83.78,"history":{}},{"question":"om du vill vara för dig själv på förskolan/ familjedaghemmet, kan du det då?","area":null,"gr":null,"goteborg":null,"district":2.16024,"school":2.02703,"normalized":51.35,"history":{}},{"question":"tycker du om personalen på förskolan/familjedaghemmet?","area":null,"gr":null,"goteborg":null,"district":2.83301,"school":2.94595,"normalized":97.3,"history":{}},{"question":"brukar du få lära dig nya saker på förskolan/familjedaghemmet?","area":null,"gr":null,"goteborg":null,"district":2.68091,"school":2.64865,"normalized":82.43,"history":{}},{"question":"vad tycker du om maten på förskolan/familjedaghemmet?","area":null,"gr":null,"goteborg":null,"district":2.63972,"school":2.67568,"normalized":83.78,"history":{}}],"responses":[{"question":"tycker du att det är roligt att vara på förskolan/ familjedaghemmet?","stronglyAgree":68.42105,"agree":null,"neither":28.94737,"disagree":null,"stronglyDisagree":2.63158,"dontKnow":null},{"question":"har du några bra kompisar på förskolan/ familjedaghemmet?","stronglyAgree":94.59459,"agree":null,"neither":5.40541,"disagree":null,"stronglyDisagree":0,"dontKnow":null},{"question":"brukar ni göra roliga saker när ni är inne på förskolan/ familjedaghemmet?","stronglyAgree":97.2973,"agree":null,"neither":2.7027,"disagree":null,"stronglyDisagree":0,"dontKnow":null},{"question":"får du själv bestämma vad du vill leka på förskolan/ familjedaghemmet?","stronglyAgree":48.57143,"agree":null,"neither":42.85714,"disagree":null,"stronglyDisagree":8.57143,"dontKnow":null},{"question":"finns det roliga saker att leka med på förskolan/ familjedaghemmet?","stronglyAgree":83.78378,"agree":null,"neither":10.81081,"disagree":null,"stronglyDisagree":5.40541,"dontKnow":null},{"question":"vad tycker du om att vara ute och leka på förskolan/familjedaghemmet?","stronglyAgree":70.27027,"agree":null,"neither":27.02703,"disagree":null,"stronglyDisagree":2.7027,"dontKnow":null},{"question":"om du vill vara för dig själv på förskolan/ familjedaghemmet, kan du det då?","stronglyAgree":37.83784,"agree":null,"neither":27.02703,"disagree":null,"stronglyDisagree":35.13514,"dontKnow":null},{"question":"tycker du om personalen på förskolan/familjedaghemmet?","stronglyAgree":94.59459,"agree":null,"neither":5.40541,"disagree":null,"stronglyDisagree":0,"dontKnow":null},{"question":"brukar du få lära dig nya saker på förskolan/familjedaghemmet?","stronglyAgree":70.27027,"agree":null,"neither":24.32432,"disagree":null,"stronglyDisagree":5.40541,"dontKnow":null},{"question":"vad tycker du om maten på förskolan/familjedaghemmet?","stronglyAgree":67.56757,"agree":null,"neither":32.43243,"disagree":null,"stronglyDisagree":0,"dontKnow":null}],"genderSplit":[],"importantQuestions":[],"unitMeans":[],"relatedReports":[{"reportId":30382,"reportType":"unit","unitName":"HÄSTEVIK (S)","schoolName":"Hästevik (s)"}]}