{"id":16707,"schoolId":8608,"schoolName":"Enhet Grimmered, Ängåsg.","areaName":"11_Älvsborg","year":2007,"reportType":"unit","unitName":"Enhet Grimmered, Ängåsg.","pdfUrl":"https://enkater.goteborg.se/2007/BARN__F%c3%96RSKOLA/11_%c3%84lvsborg/%c3%84lvsborg%20Barn_tabell1_kom_2007_del1.xls#T1011020303","scale":"1-3","metadata":{"responseRate":null,"respondents":20,"totalInvited":null,"birthYearDistribution":null,"childGenderDistribution":null,"parentGenderDistribution":null},"means":[{"question":"tycker du att det är roligt att vara på förskolan/ familjedaghemmet?","area":null,"gr":null,"goteborg":null,"district":2.7716,"school":2.89474,"normalized":94.74,"history":{}},{"question":"har du några bra kompisar på förskolan/ familjedaghemmet?","area":null,"gr":null,"goteborg":null,"district":2.875,"school":3,"normalized":100,"history":{}},{"question":"brukar ni göra roliga saker när ni är inne på förskolan/ familjedaghemmet?","area":null,"gr":null,"goteborg":null,"district":2.83798,"school":2.78947,"normalized":89.47,"history":{}},{"question":"får du själv bestämma vad du vill leka på förskolan/ familjedaghemmet?","area":null,"gr":null,"goteborg":null,"district":2.50416,"school":2.52632,"normalized":76.32,"history":{}},{"question":"finns det roliga saker att leka med på förskolan/ familjedaghemmet?","area":null,"gr":null,"goteborg":null,"district":2.79144,"school":2.89474,"normalized":94.74,"history":{}},{"question":"vad tycker du om att vara ute och leka på förskolan/familjedaghemmet?","area":null,"gr":null,"goteborg":null,"district":2.63736,"school":2.63158,"normalized":81.58,"history":{}},{"question":"om du vill vara för dig själv på förskolan/ familjedaghemmet, kan du det då?","area":null,"gr":null,"goteborg":null,"district":2.17654,"school":2.31579,"normalized":65.79,"history":{}},{"question":"tycker du om personalen på förskolan/familjedaghemmet?","area":null,"gr":null,"goteborg":null,"district":2.83515,"school":2.78947,"normalized":89.47,"history":{}},{"question":"brukar du få lära dig nya saker på förskolan/familjedaghemmet?","area":null,"gr":null,"goteborg":null,"district":2.66811,"school":2.84211,"normalized":92.11,"history":{}},{"question":"vad tycker du om maten på förskolan/familjedaghemmet?","area":null,"gr":null,"goteborg":null,"district":2.62478,"school":2.68421,"normalized":84.21,"history":{}}],"responses":[{"question":"tycker du att det är roligt att vara på förskolan/ familjedaghemmet?","stronglyAgree":89.47368,"agree":null,"neither":10.52632,"disagree":null,"stronglyDisagree":0,"dontKnow":null},{"question":"har du några bra kompisar på förskolan/ familjedaghemmet?","stronglyAgree":100,"agree":null,"neither":0,"disagree":null,"stronglyDisagree":0,"dontKnow":null},{"question":"brukar ni göra roliga saker när ni är inne på förskolan/ familjedaghemmet?","stronglyAgree":84.21053,"agree":null,"neither":10.52632,"disagree":null,"stronglyDisagree":5.26316,"dontKnow":null},{"question":"får du själv bestämma vad du vill leka på förskolan/ familjedaghemmet?","stronglyAgree":63.15789,"agree":null,"neither":26.31579,"disagree":null,"stronglyDisagree":10.52632,"dontKnow":null},{"question":"finns det roliga saker att leka med på förskolan/ familjedaghemmet?","stronglyAgree":89.47368,"agree":null,"neither":10.52632,"disagree":null,"stronglyDisagree":0,"dontKnow":null},{"question":"vad tycker du om att vara ute och leka på förskolan/familjedaghemmet?","stronglyAgree":73.68421,"agree":null,"neither":15.78947,"disagree":null,"stronglyDisagree":10.52632,"dontKnow":null},{"question":"om du vill vara för dig själv på förskolan/ familjedaghemmet, kan du det då?","stronglyAgree":52.63158,"agree":null,"neither":26.31579,"disagree":null,"stronglyDisagree":21.05263,"dontKnow":null},{"question":"tycker du om personalen på förskolan/familjedaghemmet?","stronglyAgree":78.94737,"agree":null,"neither":21.05263,"disagree":null,"stronglyDisagree":0,"dontKnow":null},{"question":"brukar du få lära dig nya saker på förskolan/familjedaghemmet?","stronglyAgree":84.21053,"agree":null,"neither":15.78947,"disagree":null,"stronglyDisagree":0,"dontKnow":null},{"question":"vad tycker du om maten på förskolan/familjedaghemmet?","stronglyAgree":68.42105,"agree":null,"neither":31.57895,"disagree":null,"stronglyDisagree":0,"dontKnow":null}],"genderSplit":[],"importantQuestions":[],"unitMeans":[],"relatedReports":[{"reportId":13970,"reportType":"school","unitName":null,"schoolName":"Älvsborg Barn_tabell1_kom_2007_del1.xls"},{"reportId":16701,"reportType":"unit","unitName":"Enh Långedrag, Bygatan 13C","schoolName":"Enh Långedrag, Bygatan 13C"},{"reportId":16702,"reportType":"unit","unitName":"Enh Långedrag, Tandkulleg. 7","schoolName":"Enh Långedrag, Tandkulleg. 7"},{"reportId":16703,"reportType":"unit","unitName":"Enh Fiskebäck, Fredagsomten 23","schoolName":"Enh Fiskebäck, Fredagsomten 23"},{"reportId":16704,"reportType":"unit","unitName":"Enh Fiskebäck, N. Flundreg. 23","schoolName":"Enh Fiskebäck, N. Flundreg. 23"},{"reportId":16705,"reportType":"unit","unitName":"Enhet Grimmered, Lonsegården","schoolName":"Enhet Grimmered, Lonsegården"},{"reportId":16706,"reportType":"unit","unitName":"Enhet Grimmered, Ringblommeg.","schoolName":"Enhet Grimmered, Ringblommeg."},{"reportId":16708,"reportType":"unit","unitName":"Enhet Hagen, Långedragsv","schoolName":"Enhet Hagen, Långedragsv"},{"reportId":16709,"reportType":"unit","unitName":"Enhet Hagen, Redeg","schoolName":"Enhet Hagen, Redeg"},{"reportId":16710,"reportType":"unit","unitName":"Enhet Hagen, Stengetsg","schoolName":"Enhet Hagen, Stengetsg"},{"reportId":16711,"reportType":"unit","unitName":"Enhet Hagen, Ö.Palmgrensg","schoolName":"Enhet Hagen, Ö.Palmgrensg"},{"reportId":16712,"reportType":"unit","unitName":"Enhet Hagenskolan, Hagens Kapellväg","schoolName":"Enhet Hagenskolan, Hagens Kapellväg"},{"reportId":16713,"reportType":"unit","unitName":"Enhet Nya Varvets skola, Nya Varvets förskola","schoolName":"Enhet Nya Varvets skola, Nya Varvets förskola"},{"reportId":16714,"reportType":"unit","unitName":"Enhet Dalaskolan, Svetsaregatan","schoolName":"Enhet Dalaskolan, Svetsaregatan"}]}