{"id":16768,"schoolId":6622,"schoolName":"Låssby (N)","areaName":"16_Torslanda","year":2007,"reportType":"unit","unitName":"Låssby (N)","pdfUrl":"https://enkater.goteborg.se/2007/BARN__F%c3%96RSKOLA/16_Torslanda/Torslanda%20Barn_tabell1_kom_2007_del2.xls#T1016020206","scale":"1-3","metadata":{"responseRate":null,"respondents":62,"totalInvited":null,"birthYearDistribution":null,"childGenderDistribution":null,"parentGenderDistribution":null},"means":[{"question":"tycker du att det är roligt att vara på förskolan/ familjedaghemmet?","area":null,"gr":null,"goteborg":null,"district":2.7716,"school":2.82258,"normalized":91.13,"history":{}},{"question":"har du några bra kompisar på förskolan/ familjedaghemmet?","area":null,"gr":null,"goteborg":null,"district":2.875,"school":2.95161,"normalized":97.58,"history":{}},{"question":"brukar ni göra roliga saker när ni är inne på förskolan/ familjedaghemmet?","area":null,"gr":null,"goteborg":null,"district":2.83798,"school":3,"normalized":100,"history":{}},{"question":"får du själv bestämma vad du vill leka på förskolan/ familjedaghemmet?","area":null,"gr":null,"goteborg":null,"district":2.50416,"school":2.58065,"normalized":79.03,"history":{}},{"question":"finns det roliga saker att leka med på förskolan/ familjedaghemmet?","area":null,"gr":null,"goteborg":null,"district":2.79144,"school":2.91935,"normalized":95.97,"history":{}},{"question":"vad tycker du om att vara ute och leka på förskolan/familjedaghemmet?","area":null,"gr":null,"goteborg":null,"district":2.63736,"school":2.51613,"normalized":75.81,"history":{}},{"question":"om du vill vara för dig själv på förskolan/ familjedaghemmet, kan du det då?","area":null,"gr":null,"goteborg":null,"district":2.17654,"school":2.17742,"normalized":58.87,"history":{}},{"question":"tycker du om personalen på förskolan/familjedaghemmet?","area":null,"gr":null,"goteborg":null,"district":2.83515,"school":2.80645,"normalized":90.32,"history":{}},{"question":"brukar du få lära dig nya saker på förskolan/familjedaghemmet?","area":null,"gr":null,"goteborg":null,"district":2.66811,"school":2.74194,"normalized":87.1,"history":{}},{"question":"vad tycker du om maten på förskolan/familjedaghemmet?","area":null,"gr":null,"goteborg":null,"district":2.62478,"school":2.72581,"normalized":86.29,"history":{}}],"responses":[{"question":"tycker du att det är roligt att vara på förskolan/ familjedaghemmet?","stronglyAgree":87.09677,"agree":null,"neither":8.06452,"disagree":null,"stronglyDisagree":4.83871,"dontKnow":null},{"question":"har du några bra kompisar på förskolan/ familjedaghemmet?","stronglyAgree":96.77419,"agree":null,"neither":1.6129,"disagree":null,"stronglyDisagree":1.6129,"dontKnow":null},{"question":"brukar ni göra roliga saker när ni är inne på förskolan/ familjedaghemmet?","stronglyAgree":100,"agree":null,"neither":0,"disagree":null,"stronglyDisagree":0,"dontKnow":null},{"question":"får du själv bestämma vad du vill leka på förskolan/ familjedaghemmet?","stronglyAgree":64.51613,"agree":null,"neither":29.03226,"disagree":null,"stronglyDisagree":6.45161,"dontKnow":null},{"question":"finns det roliga saker att leka med på förskolan/ familjedaghemmet?","stronglyAgree":93.54839,"agree":null,"neither":4.83871,"disagree":null,"stronglyDisagree":1.6129,"dontKnow":null},{"question":"vad tycker du om att vara ute och leka på förskolan/familjedaghemmet?","stronglyAgree":64.51613,"agree":null,"neither":22.58065,"disagree":null,"stronglyDisagree":12.90323,"dontKnow":null},{"question":"om du vill vara för dig själv på förskolan/ familjedaghemmet, kan du det då?","stronglyAgree":45.16129,"agree":null,"neither":27.41935,"disagree":null,"stronglyDisagree":27.41935,"dontKnow":null},{"question":"tycker du om personalen på förskolan/familjedaghemmet?","stronglyAgree":83.87097,"agree":null,"neither":12.90323,"disagree":null,"stronglyDisagree":3.22581,"dontKnow":null},{"question":"brukar du få lära dig nya saker på förskolan/familjedaghemmet?","stronglyAgree":79.03226,"agree":null,"neither":16.12903,"disagree":null,"stronglyDisagree":4.83871,"dontKnow":null},{"question":"vad tycker du om maten på förskolan/familjedaghemmet?","stronglyAgree":74.19355,"agree":null,"neither":24.19355,"disagree":null,"stronglyDisagree":1.6129,"dontKnow":null}],"genderSplit":[],"importantQuestions":[],"unitMeans":[],"relatedReports":[{"reportId":30026,"reportType":"unit","unitName":"Låssby (N)","schoolName":"Låssby (N)"}]}