{"id":391,"schoolId":132,"schoolName":"Levgrensvägen 3 förskola","areaName":"Centrum område 1","year":2025,"reportType":"school","unitName":null,"pdfUrl":"https://enkater.goteborg.se/2025/BARN__F%c3%96RSKOLA/Centrum%20omr%c3%a5de%201/Levgrensv%c3%a4gen%203%20f%c3%b6rskola/Levgrensv%c3%a4gen%203%20f%c3%b6rskola_uppskal.pdf","scale":"1-5","metadata":{"responseRate":49,"respondents":43,"totalInvited":87,"birthYearDistribution":{},"childGenderDistribution":{},"parentGenderDistribution":{}},"means":[{"question":"mitt barn trivs på förskolan","area":"Trygghet och trivsel","gr":4.57,"goteborg":4.51,"district":4.48,"school":4.6,"normalized":90,"history":{"2020":4.44,"2021":4.51,"2022":4.33,"2023":4.31,"2024":4.54}},{"question":"mitt barn känner sig tryggt på förskolan","area":"Trygghet och trivsel","gr":4.53,"goteborg":4.48,"district":4.43,"school":4.58,"normalized":89.5,"history":{"2020":4.37,"2021":4.36,"2022":4.27,"2023":4.39,"2024":4.35}},{"question":"förskolan stimulerar barnens samspel i grupp","area":"Trygghet och trivsel","gr":4.46,"goteborg":4.39,"district":4.33,"school":4.46,"normalized":86.5,"history":{"2020":4.26,"2021":4.39,"2022":4.36,"2023":4.26,"2024":4.4}},{"question":"mitt barn känner den personal som möter dem på förskolan","area":"Trygghet och trivsel","gr":4.49,"goteborg":4.43,"district":4.36,"school":4.56,"normalized":89,"history":{"2020":4.31,"2021":4.36,"2022":4.23,"2023":4.44,"2024":4.42}},{"question":"personalen bemöter mitt barn på ett sätt som passar barnet","area":"Trygghet och trivsel","gr":4.48,"goteborg":4.41,"district":4.36,"school":4.5,"normalized":87.5,"history":{"2020":4.37,"2021":4.36,"2022":4.29,"2023":4.26,"2024":4.25}},{"question":"barnen ges lika möjligheter att utvecklas oberoende av kön, etnisk tillhörighet, religion eller funktionsnedsättning","area":"Trygghet och trivsel","gr":4.55,"goteborg":4.48,"district":4.43,"school":4.5,"normalized":87.5,"history":{"2020":4.39,"2021":4.41,"2022":4.49,"2023":4.37,"2024":4.56}},{"question":"mitt barn ges möjlighet att bearbeta konflikter, reda ut missförstånd, kompromissa och respektera varandra","area":"Trygghet och trivsel","gr":4.35,"goteborg":4.29,"district":4.21,"school":4.28,"normalized":82,"history":{"2020":4.05,"2021":4.08,"2022":4.29,"2023":4.07,"2024":4.17}},{"question":"språkutveckling och kommunikation","area":"Utveckling och lärande","gr":4.48,"goteborg":4.4,"district":4.36,"school":4.62,"normalized":90.5,"history":{"2020":4.14,"2021":4.45,"2022":4.43,"2023":4.45,"2024":4.22}},{"question":"förskolan ger det stöd som mitt barn behöver","area":"Utveckling och lärande","gr":4.38,"goteborg":4.31,"district":4.21,"school":4.26,"normalized":81.5,"history":{"2020":4.26,"2021":4.24,"2022":4.11,"2023":4.23,"2024":4.13}},{"question":"förskolan ger den stimulans som mitt barn behöver","area":"Utveckling och lärande","gr":4.37,"goteborg":4.28,"district":4.16,"school":4.3,"normalized":82.5,"history":{"2020":4.08,"2021":4.24,"2022":4.27,"2023":4.3,"2024":4.36}},{"question":"mitt barns förskola uppmuntrar till lek, utveckling och lärande","area":"Utveckling och lärande","gr":4.55,"goteborg":4.48,"district":4.41,"school":4.63,"normalized":90.75,"history":{"2020":4.35,"2021":4.63,"2022":4.37,"2023":4.5,"2024":4.55}},{"question":"mitt barns förskola har en utemiljö som är inspirerande och inbjudande","area":"Utveckling och lärande","gr":3.99,"goteborg":3.94,"district":3.75,"school":4.33,"normalized":83.25,"history":{"2020":4.39,"2021":4.42,"2022":4.35,"2023":4.52,"2024":4.44}},{"question":"mitt barns förskola har en innemiljö som är inspirerande och inbjudande","area":"Utveckling och lärande","gr":4.18,"goteborg":4.12,"district":3.89,"school":4.19,"normalized":79.75,"history":{"2020":4.14,"2021":4.27,"2022":4.4,"2023":4.36,"2024":4.29}},{"question":"förmåga att skapa och uttrycka sig i olika former, exempelvis genom bild, form, rörelse, sång, musik, dans, drama","area":"Utveckling och lärande","gr":4.52,"goteborg":4.45,"district":4.35,"school":4.6,"normalized":90,"history":{"2020":4.12,"2021":4.4,"2022":4.47,"2023":4.51,"2024":4.42}},{"question":"förståelse för hur egna handlingar kan påverka miljön och bidra till en hållbar utveckling","area":"Utveckling och lärande","gr":4.29,"goteborg":4.21,"district":4.06,"school":4.26,"normalized":81.5,"history":{"2020":3.9,"2021":4.18,"2022":4.25,"2023":4.14,"2024":4.06}},{"question":"förskolan arbetar med att barnen oavsett könstillhörighet ges samma möjligheter, att pröva och utveckla vad de är bra på och vad de är intresserade av","area":"Utveckling och lärande","gr":4.57,"goteborg":4.51,"district":4.48,"school":4.66,"normalized":91.5,"history":{"2020":4.52,"2021":4.6,"2022":4.45,"2023":4.34,"2024":4.31}},{"question":"matematiska tänkande för att undersöka och reflektera, exempelvis genom användande av begrepp, form, mängd och sortering","area":"Utveckling och lärande","gr":4.35,"goteborg":4.26,"district":4.18,"school":4.53,"normalized":88.25,"history":{"2020":4.09,"2021":4.39,"2022":4.37,"2023":4.41,"2024":4.29}},{"question":"förståelse för teknik och naturvetenskapliga fenomen, exempelvis genom samtal om kroppen, djur och natur eller genom olika experiment","area":"Utveckling och lärande","gr":4.37,"goteborg":4.29,"district":4.14,"school":4.45,"normalized":86.25,"history":{"2020":4.14,"2021":4.3,"2022":4.36,"2023":4.31,"2024":4.27}},{"question":"jag upplever att mitt barn får använda digitala verktyg på ett sätt som stimulerar utveckling och lärande.","area":"Utveckling och lärande","gr":3.92,"goteborg":3.84,"district":3.58,"school":3.79,"normalized":69.75,"history":{"2020":3.7,"2021":3.66,"2022":3.75,"2023":4,"2024":3.77}},{"question":"förskolan uppmuntrar mitt barn att uttrycka sina tankar och åsikter","area":"Inflytande","gr":4.42,"goteborg":4.36,"district":4.3,"school":4.42,"normalized":85.5,"history":{"2020":4.13,"2021":4.32,"2022":4.13,"2023":4.17,"2024":4.16}},{"question":"förskolan tar hänsyn till mitt barns behov och intressen","area":"Inflytande","gr":4.37,"goteborg":4.29,"district":4.21,"school":4.27,"normalized":81.75,"history":{"2020":4.06,"2021":4.27,"2022":4.04,"2023":4.24,"2024":4.17}},{"question":"förskolan informerar om mål och innehåll i utbildningen","area":"Relation och kommunikation","gr":4.3,"goteborg":4.23,"district":4.09,"school":4.44,"normalized":86,"history":{"2020":4.02,"2021":3.81,"2022":3.78,"2023":4.26,"2024":4.29}},{"question":"utvecklingssamtalet ger mig möjlighet till en god dialog kring mitt barns trivsel, utveckling och lärande","area":"Relation och kommunikation","gr":4.33,"goteborg":4.22,"district":4.12,"school":4.31,"normalized":82.75,"history":{"2020":4.11,"2021":4.16,"2022":4,"2023":4.33,"2024":4.15}},{"question":"jag känner mig välkommen att ställa frågor och komma med synpunkter","area":"Relation och kommunikation","gr":4.43,"goteborg":4.34,"district":4.29,"school":4.33,"normalized":83.25,"history":{"2020":4.24,"2021":4.29,"2022":4.31,"2023":4.29,"2024":4.35}},{"question":"jag känner mig trygg med att mitt barn blir väl omhändertaget på förskolan.","area":"Relation och kommunikation","gr":4.52,"goteborg":4.44,"district":4.38,"school":4.56,"normalized":89,"history":{"2020":4.39,"2021":4.42,"2022":4.41,"2023":4.28,"2024":4.44}},{"question":"förskolan tar hänsyn till den information jag förmedlar om mitt barn, till exempel om barnets mående, familjesituation eller utveckling","area":"Relation och kommunikation","gr":4.44,"goteborg":4.36,"district":4.32,"school":4.38,"normalized":84.5,"history":{"2020":4.39,"2021":4.35,"2022":4.22,"2023":4.31,"2024":4.17}},{"question":"jag är nöjd med mitt barns förskola.","area":"Helhetsomdöme","gr":4.44,"goteborg":4.34,"district":4.22,"school":4.56,"normalized":89,"history":{"2020":4.25,"2021":4.45,"2022":4.35,"2023":4.27,"2024":4.29}},{"question":"jag kan rekommendera mitt barns förskola till andra vårdnadshavare.","area":"Helhetsomdöme","gr":4.42,"goteborg":4.31,"district":4.18,"school":4.51,"normalized":87.75,"history":{"2020":4.14,"2021":4.44,"2022":4.36,"2023":4.28,"2024":4.31}}],"responses":[{"question":"mitt barn trivs på förskolan","stronglyAgree":60,"agree":40,"neither":null,"disagree":null,"stronglyDisagree":null,"dontKnow":null},{"question":"språkutveckling och kommunikation","stronglyAgree":65,"agree":28,"neither":null,"disagree":null,"stronglyDisagree":null,"dontKnow":null},{"question":"mitt barn känner sig tryggt på förskolan","stronglyAgree":58,"agree":42,"neither":null,"disagree":null,"stronglyDisagree":null,"dontKnow":null},{"question":"förskolan stimulerar barnens samspel i grupp","stronglyAgree":51,"agree":37,"neither":7,"disagree":null,"stronglyDisagree":null,"dontKnow":null},{"question":"förskolan ger det stöd som mitt barn behöver","stronglyAgree":40,"agree":47,"neither":14,"disagree":null,"stronglyDisagree":null,"dontKnow":null},{"question":"förskolan ger den stimulans som mitt barn behöver","stronglyAgree":47,"agree":40,"neither":12,"disagree":null,"stronglyDisagree":null,"dontKnow":null},{"question":"mitt barn känner den personal som möter dem på förskolan","stronglyAgree":58,"agree":40,"neither":null,"disagree":null,"stronglyDisagree":null,"dontKnow":null},{"question":"personalen bemöter mitt barn på ett sätt som passar barnet","stronglyAgree":56,"agree":35,"neither":7,"disagree":null,"stronglyDisagree":null,"dontKnow":null},{"question":"mitt barns förskola uppmuntrar till lek, utveckling och lärande","stronglyAgree":65,"agree":33,"neither":null,"disagree":null,"stronglyDisagree":null,"dontKnow":null},{"question":"förskolan uppmuntrar mitt barn att uttrycka sina tankar och åsikter","stronglyAgree":49,"agree":28,"neither":12,"disagree":null,"stronglyDisagree":null,"dontKnow":12},{"question":"förskolan tar hänsyn till mitt barns behov och intressen","stronglyAgree":47,"agree":28,"neither":21,"disagree":null,"stronglyDisagree":null,"dontKnow":null},{"question":"förskolan informerar om mål och innehåll i utbildningen","stronglyAgree":56,"agree":33,"neither":12,"disagree":null,"stronglyDisagree":null,"dontKnow":null},{"question":"barnen ges lika möjligheter att utvecklas oberoende av kön, etnisk tillhörighet, religion eller funktionsnedsättning","stronglyAgree":51,"agree":30,"neither":7,"disagree":null,"stronglyDisagree":null,"dontKnow":12},{"question":"mitt barns förskola har en utemiljö som är inspirerande och inbjudande","stronglyAgree":51,"agree":35,"neither":9,"disagree":null,"stronglyDisagree":null,"dontKnow":null},{"question":"mitt barns förskola har en innemiljö som är inspirerande och inbjudande","stronglyAgree":42,"agree":42,"neither":9,"disagree":7,"stronglyDisagree":null,"dontKnow":null},{"question":"förmåga att skapa och uttrycka sig i olika former, exempelvis genom bild, form, rörelse, sång, musik, dans, drama","stronglyAgree":63,"agree":30,"neither":null,"disagree":null,"stronglyDisagree":null,"dontKnow":null},{"question":"utvecklingssamtalet ger mig möjlighet till en god dialog kring mitt barns trivsel, utveckling och lärande","stronglyAgree":56,"agree":26,"neither":12,"disagree":null,"stronglyDisagree":null,"dontKnow":null},{"question":"jag känner mig välkommen att ställa frågor och komma med synpunkter","stronglyAgree":56,"agree":28,"neither":7,"disagree":null,"stronglyDisagree":null,"dontKnow":null},{"question":"jag känner mig trygg med att mitt barn blir väl omhändertaget på förskolan.","stronglyAgree":63,"agree":30,"neither":7,"disagree":null,"stronglyDisagree":null,"dontKnow":null},{"question":"mitt barn ges möjlighet att bearbeta konflikter, reda ut missförstånd, kompromissa och respektera varandra","stronglyAgree":37,"agree":35,"neither":9,"disagree":null,"stronglyDisagree":null,"dontKnow":16},{"question":"förskolan arbetar med att barnen oavsett könstillhörighet ges samma möjligheter, att pröva och utveckla vad de är bra på och vad de är intresserade av","stronglyAgree":58,"agree":30,"neither":null,"disagree":null,"stronglyDisagree":null,"dontKnow":12},{"question":"matematiska tänkande för att undersöka och reflektera, exempelvis genom användande av begrepp, form, mängd och sortering","stronglyAgree":49,"agree":44,"neither":null,"disagree":null,"stronglyDisagree":null,"dontKnow":7},{"question":"förståelse för teknik och naturvetenskapliga fenomen, exempelvis genom samtal om kroppen, djur och natur eller genom olika experiment","stronglyAgree":44,"agree":47,"neither":null,"disagree":null,"stronglyDisagree":null,"dontKnow":7},{"question":"förskolan tar hänsyn till den information jag förmedlar om mitt barn, till exempel om barnets mående, familjesituation eller utveckling","stronglyAgree":58,"agree":23,"neither":12,"disagree":null,"stronglyDisagree":null,"dontKnow":null},{"question":"jag är nöjd med mitt barns förskola.","stronglyAgree":63,"agree":30,"neither":7,"disagree":null,"stronglyDisagree":null,"dontKnow":null},{"question":"jag kan rekommendera mitt barns förskola till andra vårdnadshavare.","stronglyAgree":63,"agree":28,"neither":7,"disagree":null,"stronglyDisagree":null,"dontKnow":null}],"genderSplit":[{"question":"mitt barn trivs på förskolan","total":100,"flicka":100,"pojke":100},{"question":"språkutveckling och kommunikation","total":93,"flicka":94,"pojke":92},{"question":"mitt barn känner sig tryggt på förskolan","total":100,"flicka":100,"pojke":100},{"question":"förskolan stimulerar barnens samspel i grupp","total":88,"flicka":89,"pojke":88},{"question":"förskolan ger det stöd som mitt barn behöver","total":86,"flicka":89,"pojke":83},{"question":"förskolan ger den stimulans som mitt barn behöver","total":86,"flicka":89,"pojke":83},{"question":"mitt barn känner den personal som möter dem på förskolan","total":98,"flicka":100,"pojke":96},{"question":"personalen bemöter mitt barn på ett sätt som passar barnet","total":91,"flicka":83,"pojke":96},{"question":"mitt barns förskola uppmuntrar till lek, utveckling och lärande","total":98,"flicka":100,"pojke":96},{"question":"förskolan uppmuntrar mitt barn att uttrycka sina tankar och åsikter","total":77,"flicka":89,"pojke":71},{"question":"förskolan tar hänsyn till mitt barns behov och intressen","total":74,"flicka":78,"pojke":75},{"question":"förskolan informerar om mål och innehåll i utbildningen","total":88,"flicka":94,"pojke":83},{"question":"barnen ges lika möjligheter att utvecklas oberoende av kön, etnisk tillhörighet, religion eller funktionsnedsättning","total":81,"flicka":78,"pojke":88},{"question":"mitt barns förskola har en utemiljö som är inspirerande och inbjudande","total":86,"flicka":89,"pojke":83},{"question":"mitt barns förskola har en innemiljö som är inspirerande och inbjudande","total":84,"flicka":83,"pojke":88},{"question":"förmåga att skapa och uttrycka sig i olika former, exempelvis genom bild, form, rörelse, sång, musik, dans, drama","total":93,"flicka":100,"pojke":88},{"question":"förståelse för hur egna handlingar kan påverka miljön och bidra till en hållbar utveckling","total":70,"flicka":56,"pojke":83},{"question":"utvecklingssamtalet ger mig möjlighet till en god dialog kring mitt barns trivsel, utveckling och lärande","total":81,"flicka":78,"pojke":88},{"question":"jag känner mig välkommen att ställa frågor och komma med synpunkter","total":84,"flicka":78,"pojke":88},{"question":"jag känner mig trygg med att mitt barn blir väl omhändertaget på förskolan.","total":93,"flicka":94,"pojke":96},{"question":"mitt barn ges möjlighet att bearbeta konflikter, reda ut missförstånd, kompromissa och respektera varandra","total":72,"flicka":61,"pojke":83},{"question":"matematiska tänkande för att undersöka och reflektera, exempelvis genom användande av begrepp, form, mängd och sortering","total":93,"flicka":89,"pojke":100},{"question":"förståelse för teknik och naturvetenskapliga fenomen, exempelvis genom samtal om kroppen, djur och natur eller genom olika experiment","total":91,"flicka":83,"pojke":100},{"question":"jag upplever att mitt barn får använda digitala verktyg på ett sätt som stimulerar utveckling och lärande.","total":40,"flicka":33,"pojke":46},{"question":"förskolan tar hänsyn till den information jag förmedlar om mitt barn, till exempel om barnets mående, familjesituation eller utveckling","total":81,"flicka":83,"pojke":79},{"question":"jag är nöjd med mitt barns förskola.","total":93,"flicka":89,"pojke":100},{"question":"jag kan rekommendera mitt barns förskola till andra vårdnadshavare.","total":91,"flicka":89,"pojke":96}],"importantQuestions":[{"question":"mitt barn känner sig tryggt på förskolan","rank":1,"pct":72},{"question":"mitt barn trivs på förskolan","rank":2,"pct":56},{"question":"jag känner mig trygg med att mitt barn blir väl omhändertaget på förskolan","rank":3,"pct":42},{"question":"förskolan ger den stimulans som mitt barn behöver","rank":4,"pct":30},{"question":"mitt barns förskola uppmuntrar till lek, utveckling och lärande","rank":5,"pct":28}],"unitMeans":[{"unit":"Gul","area":"Trygghet och trivsel","mean":4.26},{"unit":"Gul","area":"Utveckling och lärande","mean":3.96},{"unit":"Gul","area":"Inflytande","mean":4.16},{"unit":"Gul","area":"Relation och kommunikation","mean":4.05},{"unit":"Gul","area":"Helhetsomdöme","mean":4.02},{"unit":"Gul","area":"Övergripande","mean":4.42},{"unit":"Levgrensvägen 3 förskola","area":"Trygghet och trivsel","mean":4.5},{"unit":"Levgrensvägen 3 förskola","area":"Utveckling och lärande","mean":4.27},{"unit":"Levgrensvägen 3 förskola","area":"Inflytande","mean":4.47},{"unit":"Levgrensvägen 3 förskola","area":"Relation och kommunikation","mean":4.34},{"unit":"Levgrensvägen 3 förskola","area":"Helhetsomdöme","mean":4.41},{"unit":"Levgrensvägen 3 förskola","area":"Övergripande","mean":4.53},{"unit":"Röd","area":"Trygghet och trivsel","mean":4.63},{"unit":"Röd","area":"Utveckling och lärande","mean":4.28},{"unit":"Röd","area":"Inflytande","mean":4.65},{"unit":"Röd","area":"Relation och kommunikation","mean":4.25},{"unit":"Röd","area":"Helhetsomdöme","mean":4.65},{"unit":"Röd","area":"Övergripande","mean":4.39},{"unit":"Turkos","area":"Trygghet och trivsel","mean":4.46},{"unit":"Turkos","area":"Utveckling och lärande","mean":4.25},{"unit":"Turkos","area":"Inflytande","mean":4.5},{"unit":"Turkos","area":"Relation och kommunikation","mean":4.35},{"unit":"Turkos","area":"Helhetsomdöme","mean":4.5},{"unit":"Turkos","area":"Övergripande","mean":4.71}],"relatedReports":[{"reportId":390,"reportType":"unit","unitName":"Gul","schoolName":"Levgrensvägen 3 förskola"},{"reportId":392,"reportType":"unit","unitName":"Röd","schoolName":"Levgrensvägen 3 förskola"},{"reportId":393,"reportType":"unit","unitName":"Turkos","schoolName":"Levgrensvägen 3 förskola"}]}