{"id":4296,"schoolId":1561,"schoolName":"Transistorgatan 2","areaName":"Sydväst område 2","year":2023,"reportType":"unit","unitName":"Solen","pdfUrl":"https://enkater.goteborg.se/2023/BARN__F%c3%96RSKOLA/Sydv%c3%a4st%20omr%c3%a5de%202/GR,%20G%c3%b6teborg,%20Sydv%c3%a4st%202,%20Transistorgatan%202%20f%c3%b6rskola,%20Solen.pdf","scale":"1-5","metadata":{"responseRate":70,"respondents":7,"totalInvited":10,"birthYearDistribution":{},"childGenderDistribution":{},"parentGenderDistribution":{}},"means":[{"question":"mitt barn trivs på förskolan","area":"Trygghet och trivsel","gr":4.49,"goteborg":4.47,"district":4.43,"school":4.28,"normalized":82,"history":{"2020":4.5,"2021":4.73,"2022":4.55,"2023":4.57}},{"question":"mitt barn känner sig tryggt på förskolan","area":"Trygghet och trivsel","gr":4.46,"goteborg":4.44,"district":4.4,"school":4.19,"normalized":79.75,"history":{"2020":4.5,"2021":4.73,"2022":4.45,"2023":4.57}},{"question":"förskolan stimulerar barnens samspel i grupp","area":"Trygghet och trivsel","gr":4.39,"goteborg":4.35,"district":4.29,"school":4.21,"normalized":80.25,"history":{"2020":4.12,"2021":4.45,"2022":4.55,"2023":4.29}},{"question":"mitt barn känner den personal som möter dem på förskolan","area":"Trygghet och trivsel","gr":4.4,"goteborg":4.39,"district":4.28,"school":4.13,"normalized":78.25,"history":{"2020":4.75,"2021":4.64,"2022":4.36,"2023":4.57}},{"question":"personalen bemöter mitt barn på ett sätt som passar barnet","area":"Trygghet och trivsel","gr":4.38,"goteborg":4.35,"district":4.27,"school":4.28,"normalized":82,"history":{"2020":4.5,"2021":4.64,"2022":4.27,"2023":4.57}},{"question":"barnen ges lika möjligheter att utvecklas oberoende av kön, etnisk tillhörighet, religion eller funktionsnedsättning","area":"Trygghet och trivsel","gr":4.47,"goteborg":4.44,"district":4.37,"school":4.4,"normalized":85,"history":{"2020":4.12,"2021":4.55,"2022":4.45,"2023":4.43}},{"question":"mitt barn ges möjlighet att bearbeta konflikter, reda ut missförstånd, kompromissa och respektera varandra","area":"Trygghet och trivsel","gr":4.28,"goteborg":4.25,"district":4.19,"school":4.09,"normalized":77.25,"history":{"2020":3.86,"2021":4.3,"2022":4.55,"2023":4.29}},{"question":"språkutveckling och kommunikation","area":"Utveckling och lärande","gr":4.38,"goteborg":4.32,"district":4.27,"school":4.25,"normalized":81.25,"history":{"2020":4.12,"2021":4.6,"2022":4.36,"2023":4.43}},{"question":"förskolan ger det stöd som mitt barn behöver","area":"Utveckling och lärande","gr":4.29,"goteborg":4.25,"district":4.2,"school":4.17,"normalized":79.25,"history":{"2020":4.25,"2021":4.45,"2022":4.45,"2023":4.43}},{"question":"förskolan ger den stimulans som mitt barn behöver","area":"Utveckling och lärande","gr":4.27,"goteborg":4.22,"district":4.18,"school":4.18,"normalized":79.5,"history":{"2020":4.5,"2021":4.45,"2022":4.27,"2023":4.29}},{"question":"mitt barns förskola uppmuntrar till lek, utveckling och lärande","area":"Utveckling och lärande","gr":4.48,"goteborg":4.44,"district":4.41,"school":4.4,"normalized":85,"history":{"2020":4.62,"2021":4.55,"2022":4.55,"2023":4.57}},{"question":"mitt barns förskola har en utemiljö som är inspirerande och inbjudande","area":"Utveckling och lärande","gr":3.89,"goteborg":3.89,"district":3.97,"school":4.21,"normalized":80.25,"history":{"2020":4.38,"2021":4.09,"2022":4.09,"2023":4.57}},{"question":"mitt barns förskola har en innemiljö som är inspirerande och inbjudande","area":"Utveckling och lärande","gr":4.15,"goteborg":4.11,"district":4.17,"school":4.34,"normalized":83.5,"history":{"2020":4.5,"2021":4.45,"2022":4.45,"2023":4.43}},{"question":"förmåga att skapa och uttrycka sig i olika former, exempelvis genom bild, form, rörelse, sång, musik, dans, drama","area":"Utveckling och lärande","gr":4.44,"goteborg":4.41,"district":4.35,"school":4.31,"normalized":82.75,"history":{"2020":4.5,"2021":4.64,"2022":4.45,"2023":4.29}},{"question":"förståelse för hur egna handlingar kan påverka miljön och bidra till en hållbar utveckling","area":"Utveckling och lärande","gr":4.24,"goteborg":4.19,"district":4.15,"school":4.02,"normalized":75.5,"history":{"2020":4,"2021":4.22,"2022":4.18,"2023":4.29}},{"question":"matematiska tänkande för att undersöka och reflektera, exempelvis genom användande av begrepp, form, mängd och sortering","area":"Utveckling och lärande","gr":4.27,"goteborg":4.21,"district":4.18,"school":3.98,"normalized":74.5,"history":{"2020":4.14,"2021":4.5,"2022":4.09,"2023":4.14}},{"question":"förskolan arbetar med att barnen oavsett könstillhörighet ges samma möjligheter, att pröva och utveckla vad de är bra på och vad de är intresserade","area":"Utveckling och lärande","gr":4.48,"goteborg":4.45,"district":4.41,"school":4.33,"normalized":83.25,"history":{"2020":4.5,"2021":4.22,"2022":4.55,"2023":4.29}},{"question":"förståelse för teknik och naturvetenskapliga fenomen, exempelvis genom samtal om kroppen,djur och natur eller genom olika experiment","area":"Utveckling och lärande","gr":4.29,"goteborg":4.25,"district":4.2,"school":4.06,"normalized":76.5,"history":{"2020":4.14,"2021":4.6,"2022":4.09,"2023":4.14}},{"question":"jag upplever att mitt barn får använda digitala verktyg på ett sätt som stimulerar utveckling och","area":"Utveckling och lärande","gr":3.92,"goteborg":3.86,"district":3.81,"school":3.95,"normalized":73.75,"history":{"2020":4.14,"2021":4,"2022":3.8,"2023":4.33}},{"question":"förskolan uppmuntrar mitt barn att uttrycka sina tankar och åsikter","area":"Inflytande","gr":4.34,"goteborg":4.31,"district":4.27,"school":4.22,"normalized":80.5,"history":{"2020":4.12,"2021":4.64,"2022":4.45,"2023":4.57}},{"question":"förskolan tar hänsyn till mitt barns behov och intressen","area":"Inflytande","gr":4.26,"goteborg":4.23,"district":4.17,"school":4.12,"normalized":78,"history":{"2020":4.25,"2021":4.45,"2022":4.27,"2023":4.43}},{"question":"förskolan informerar om mål och innehåll i utbildningen","area":"Relation och kommunikation","gr":4.14,"goteborg":4.07,"district":3.96,"school":4.17,"normalized":79.25,"history":{"2020":4.25,"2021":4.36,"2022":4.3,"2023":4.57}},{"question":"utvecklingssamtalet ger mig möjlighet till en god dialog kring mitt barns trivsel, utveckling och lärande","area":"Relation och kommunikation","gr":4.23,"goteborg":4.16,"district":4,"school":4.18,"normalized":79.5,"history":{"2020":4.33,"2021":4.27,"2022":4.44,"2023":4.14}},{"question":"jag känner mig välkommen att ställa frågor och komma med synpunkter","area":"Relation och kommunikation","gr":4.32,"goteborg":4.27,"district":4.17,"school":4.25,"normalized":81.25,"history":{"2020":4.25,"2021":4.55,"2022":4.45,"2023":4.57}},{"question":"jag känner mig trygg med att mitt barn blir väl omhändertaget på förskolan.","area":"Relation och kommunikation","gr":4.45,"goteborg":4.4,"district":4.34,"school":4.19,"normalized":79.75,"history":{"2020":4.43,"2021":4.73,"2022":4.55,"2023":4.43}},{"question":"förskolan tar hänsyn till den information jag förmedlar om mitt barn, till exempel om barnets mående, familjesituation eller utveckling","area":"Relation och kommunikation","gr":4.34,"goteborg":4.3,"district":4.24,"school":4.21,"normalized":80.25,"history":{"2020":4.12,"2021":4.64,"2022":4.4,"2023":4.43}},{"question":"jag är nöjd med mitt barns förskola.","area":"Helhetsomdöme","gr":4.36,"goteborg":4.3,"district":4.23,"school":4.09,"normalized":77.25,"history":{"2020":4.38,"2021":4.55,"2022":4.36,"2023":4.29}},{"question":"jag kan rekommendera mitt barns förskola till andra vårdnadshavare.","area":"Helhetsomdöme","gr":4.33,"goteborg":4.27,"district":4.2,"school":4.2,"normalized":80,"history":{"2020":4.38,"2021":4.64,"2022":4.5,"2023":4.43}}],"responses":[{"question":"mitt barn trivs på förskolan","stronglyAgree":57,"agree":43,"neither":null,"disagree":null,"stronglyDisagree":null,"dontKnow":null},{"question":"språkutveckling och kommunikation","stronglyAgree":57,"agree":29,"neither":14,"disagree":null,"stronglyDisagree":null,"dontKnow":null},{"question":"mitt barn känner sig tryggt på förskolan","stronglyAgree":57,"agree":null,"neither":43,"disagree":null,"stronglyDisagree":null,"dontKnow":null},{"question":"förskolan stimulerar barnens samspel i grupp","stronglyAgree":43,"agree":43,"neither":14,"disagree":null,"stronglyDisagree":null,"dontKnow":null},{"question":"förskolan ger det stöd som mitt barn behöver","stronglyAgree":57,"agree":29,"neither":14,"disagree":null,"stronglyDisagree":null,"dontKnow":null},{"question":"förskolan ger den stimulans som mitt barn behöver","stronglyAgree":43,"agree":43,"neither":14,"disagree":null,"stronglyDisagree":null,"dontKnow":null},{"question":"mitt barn känner den personal som möter dem på förskolan","stronglyAgree":71,"agree":null,"neither":14,"disagree":14,"stronglyDisagree":null,"dontKnow":null},{"question":"personalen bemöter mitt barn på ett sätt som passar barnet","stronglyAgree":57,"agree":43,"neither":null,"disagree":null,"stronglyDisagree":null,"dontKnow":null},{"question":"mitt barns förskola uppmuntrar till lek, utveckling och lärande","stronglyAgree":57,"agree":43,"neither":null,"disagree":null,"stronglyDisagree":null,"dontKnow":null},{"question":"förskolan uppmuntrar mitt barn att uttrycka sina tankar och åsikter","stronglyAgree":57,"agree":null,"neither":43,"disagree":null,"stronglyDisagree":null,"dontKnow":null},{"question":"förskolan tar hänsyn till mitt barns behov och intressen","stronglyAgree":43,"agree":57,"neither":null,"disagree":null,"stronglyDisagree":null,"dontKnow":null},{"question":"förskolan informerar om mål och innehåll i utbildningen","stronglyAgree":57,"agree":null,"neither":43,"disagree":null,"stronglyDisagree":null,"dontKnow":null},{"question":"barnen ges lika möjligheter att utvecklas oberoende av kön, etnisk tillhörighet, religion eller funktionsnedsättning","stronglyAgree":43,"agree":57,"neither":null,"disagree":null,"stronglyDisagree":null,"dontKnow":null},{"question":"mitt barns förskola har en utemiljö som är inspirerande och inbjudande","stronglyAgree":57,"agree":null,"neither":43,"disagree":null,"stronglyDisagree":null,"dontKnow":null},{"question":"mitt barns förskola har en innemiljö som är inspirerande och inbjudande","stronglyAgree":43,"agree":57,"neither":null,"disagree":null,"stronglyDisagree":null,"dontKnow":null},{"question":"förmåga att skapa och uttrycka sig i olika former, exempelvis genom bild, form, rörelse, sång, musik, dans, drama","stronglyAgree":43,"agree":43,"neither":14,"disagree":null,"stronglyDisagree":null,"dontKnow":null},{"question":"utvecklingssamtalet ger mig möjlighet till en god dialog kring mitt barns trivsel, utveckling och lärande","stronglyAgree":43,"agree":29,"neither":29,"disagree":null,"stronglyDisagree":null,"dontKnow":null},{"question":"jag känner mig välkommen att ställa frågor och komma med synpunkter","stronglyAgree":57,"agree":null,"neither":43,"disagree":null,"stronglyDisagree":null,"dontKnow":null},{"question":"jag känner mig trygg med att mitt barn blir väl omhändertaget på förskolan.","stronglyAgree":57,"agree":29,"neither":14,"disagree":null,"stronglyDisagree":null,"dontKnow":null},{"question":"mitt barn ges möjlighet att bearbeta konflikter, reda ut missförstånd, kompromissa och respektera varandra","stronglyAgree":29,"agree":71,"neither":null,"disagree":null,"stronglyDisagree":null,"dontKnow":null},{"question":"förskolan arbetar med att barnen oavsett könstillhörighet ges samma möjligheter, att pröva och utveckla vad de är bra på och vad de är intresserade av","stronglyAgree":29,"agree":71,"neither":null,"disagree":null,"stronglyDisagree":null,"dontKnow":null},{"question":"matematiska tänkande för att undersöka och reflektera, exempelvis genom användande av begrepp, form, mängd och sortering","stronglyAgree":29,"agree":57,"neither":14,"disagree":null,"stronglyDisagree":null,"dontKnow":null},{"question":"förskolan tar hänsyn till den information jag förmedlar om mitt barn, till exempel om barnets mående, familjesituation eller utveckling","stronglyAgree":43,"agree":57,"neither":null,"disagree":null,"stronglyDisagree":null,"dontKnow":null},{"question":"jag är nöjd med mitt barns förskola.","stronglyAgree":29,"agree":71,"neither":null,"disagree":null,"stronglyDisagree":null,"dontKnow":null},{"question":"jag kan rekommendera mitt barns förskola till andra vårdnadshavare.","stronglyAgree":43,"agree":57,"neither":null,"disagree":null,"stronglyDisagree":null,"dontKnow":null},{"question":"förståelse för teknik och naturvetenskapliga fenomen, exempelvis genom samtal om kroppen,djur och natur eller genom olika experiment","stronglyAgree":29,"agree":57,"neither":14,"disagree":null,"stronglyDisagree":null,"dontKnow":null}],"genderSplit":[],"importantQuestions":[{"question":"mitt barn trivs på förskolan","rank":1,"pct":86},{"question":"mitt barn känner sig tryggt på förskolan","rank":2,"pct":71},{"question":"mitt barn känner den personal som möter dem på förskolan","rank":3,"pct":43},{"question":"personalen bemöter mitt barn på ett sätt som passar barnet","rank":4,"pct":43},{"question":"språkutveckling och kommunikation","rank":5,"pct":43}],"unitMeans":[],"relatedReports":[{"reportId":4293,"reportType":"unit","unitName":"Månen.pdf","schoolName":"Transistorgatan 2"},{"reportId":4294,"reportType":"unit","unitName":"Regnbågen.pdf","schoolName":"Transistorgatan 2"},{"reportId":4295,"reportType":"unit","unitName":"Solen 1.pdf","schoolName":"Transistorgatan 2"},{"reportId":4297,"reportType":"unit","unitName":"Stjärnan.pdf","schoolName":"Transistorgatan 2"}]}