{"id":9820,"schoolId":322,"schoolName":"Astris Gata 7 förskola","areaName":"Lundby","year":2018,"reportType":"unit","unitName":"Rapport_Mandelblom","pdfUrl":"https://enkater.goteborg.se/2018/BARN__F%c3%96RSKOLA/Lundby/Astris%20Gata%207%20f%c3%b6rskola/Rapport_Mandelblom.pdf","scale":"1-7","metadata":{"responseRate":48,"respondents":11,"totalInvited":23,"birthYearDistribution":{},"childGenderDistribution":{},"parentGenderDistribution":{}},"means":[{"question":"förskolan är rolig, trygg och lärorik för alla barn","area":"Inflytande","gr":null,"goteborg":5.7,"district":5.6,"school":4.9,"normalized":65,"history":{"2016":6.2,"2017":5.9,"2018":4.7}},{"question":"personalen tar väl hand om mitt barn","area":"Inflytande","gr":null,"goteborg":5.7,"district":5.6,"school":5,"normalized":66.67,"history":{"2016":6.1,"2017":5.6,"2018":5.3}},{"question":"personalen ger föräldrar tydlig information","area":"Inflytande","gr":null,"goteborg":5.2,"district":4.9,"school":4.3,"normalized":55,"history":{"2016":6,"2017":5.4,"2018":4.5}},{"question":"föräldrar får möjlighet att vara med och påverka arbetet i förskolan","area":"Inflytande","gr":null,"goteborg":4.9,"district":4.7,"school":4,"normalized":50,"history":{"2016":5.2,"2017":4.9,"2018":3.9}},{"question":"barnen möter personal som de känner","area":"Inflytande","gr":null,"goteborg":5.7,"district":5.5,"school":4.9,"normalized":65,"history":{"2016":5.7,"2017":5.5,"2018":5}},{"question":"barnen har möjlighet att ingå i mindre och större grupper","area":"Inflytande","gr":null,"goteborg":5.5,"district":5.3,"school":4.6,"normalized":60,"history":{"2016":5.5,"2017":4.9,"2018":4}},{"question":"barnen har möjlighet att ha inflytande på verksamhetens innehåll","area":"Inflytande","gr":null,"goteborg":5.5,"district":5.2,"school":4.6,"normalized":60,"history":{"2016":5.2,"2017":5.5,"2018":4.3}},{"question":"barnen lär sig hur man fungerar tillsammans i en grupp","area":"Inflytande","gr":null,"goteborg":5.8,"district":5.6,"school":5,"normalized":66.67,"history":{"2016":6,"2017":5.7,"2018":5.1}},{"question":"barnen får känna glädjen av att lära sig och känna att de behövs i gruppen","area":"Inflytande","gr":null,"goteborg":5.6,"district":5.5,"school":4.5,"normalized":58.33,"history":{"2016":5.4,"2017":5.5,"2018":4}},{"question":"barnen kan byta mellan olika aktiviteter under dagen","area":"Inflytande","gr":null,"goteborg":5.6,"district":5.4,"school":4.6,"normalized":60,"history":{"2016":5.5,"2017":5.5,"2018":4.5}},{"question":"barnen har möjlighet att utveckla språket","area":"Inflytande","gr":null,"goteborg":5.6,"district":5.5,"school":4.7,"normalized":61.67,"history":{"2016":5.3,"2017":5.3,"2018":4.5}},{"question":"barnen får möjlighet att utveckla förståelse för matematik","area":"Inflytande","gr":null,"goteborg":5.3,"district":5.2,"school":4.3,"normalized":55,"history":{"2016":5.2,"2017":4.8,"2018":4}},{"question":"barnen får möjlighet att utveckla förståelse för naturvetenskap","area":"Inflytande","gr":null,"goteborg":5.2,"district":5.1,"school":4.2,"normalized":53.33,"history":{"2016":4.9,"2017":5,"2018":3.9}},{"question":"flickor och pojkar har samma möjligheter","area":"Inflytande","gr":null,"goteborg":5.8,"district":5.7,"school":5,"normalized":66.67,"history":{"2016":5.4,"2017":5.5,"2018":4.8}}],"responses":[],"genderSplit":[],"importantQuestions":[],"unitMeans":[],"relatedReports":[{"reportId":9818,"reportType":"unit","unitName":"Rapport_Astris Gata 7 förskola","schoolName":"Astris Gata 7 förskola"},{"reportId":9819,"reportType":"unit","unitName":"Rapport_Kattfot","schoolName":"Astris Gata 7 förskola"},{"reportId":9821,"reportType":"unit","unitName":"Rapport_Violen","schoolName":"Astris Gata 7 förskola"}]}